apicomplexoperations/__init__.py
apicomplexoperations/main.py
complexoperations/JustSomeMath.py
complexoperations/JustSomeString.py
complexoperations/__init__.py
complexoperations_iperoyg-0.1.4.dist-info/LICENSE
complexoperations_iperoyg-0.1.4.dist-info/METADATA
complexoperations_iperoyg-0.1.4.dist-info/WHEEL
complexoperations_iperoyg-0.1.4.dist-info/top_level.txt
complexoperations_iperoyg-0.1.4.dist-info/RECORD
