Metadata-Version: 2.1
Name: complexoperations-iperoyg
Version: 0.1.4
Summary: Complex Operations Package
Author-email: Arthur Iperoyg <iperoyg@gmail.com>
Project-URL: Homepage, https://github.com/iperoyg/devops-experiments
Project-URL: Bug Tracker, https://github.com/iperoyg/devops-experiments/issues
Classifier: Programming Language :: Python :: 3
Classifier: License :: OSI Approved :: MIT License
Classifier: Operating System :: OS Independent
Requires-Python: >=3.9
License-File: LICENSE
